Workbook

Sheet README
A1: Sovereign AI compute: sizing, cost, pricing and value model
A2: Companion to esthercs.dev/research/sovereign-ai. Built 19 October 2026 by Esther Suebsubanant. Every input is dated and sourced on the Assumptions sheet.
A4: How to read this workbook
A5: Blue text | B5: Hardcoded input, sourced or labelled as my assumption on Assumptions.
A6: Black text | B6: Formula on the same sheet.
A7: Green text | B7: Formula pulling from another sheet.
A8: Yellow fill | B8: Scenario lever you are expected to change.
A9: Formula column | B9: Each computed row states its formula in words.
A11: Sheets
A12: Assumptions | B12: Every input with unit, value, read date and source URL.
A13: TopDown | B13: Three paths to 2026 sovereign AI compute spend: NVIDIA's disclosed sovereign revenue grossed up, analyst market estimates, and public funding with private leverage.
A14: BottomUp | B14: Programme by programme: announced capacity, timeline, megawatts energised in 2026, GPUs and capex, grouped by quadrant.
A15: GigawattTCO | B15: What a gigawatt costs to own, by country: capex, power, delay, and the owner's effective $ per GPU-hour.
A16: Configs | B16: Four reference builds, one per quadrant: compute exporter campus, industrial AI factory, EU gigafactory, subsidised national GPU pool.
A17: Pricing | B17: GPU-hour prices by route and region, subsidy gaps, where the margin sits.
A18: Value | B18: What the compute is worth: GDP uplift claims, revenue per compute dollar, economic value per dollar of investment.
A19: Sources | B19: Numbered source list matching the article.
A21: Units | B21: US dollars. Megawatts are IT load unless marked facility. Years are calendar years unless marked FY (NVIDIA fiscal year ends late January).

Sheet Assumptions
A1: Assumptions and inputs
A2: Blue = hardcoded. 'My assumption' = no public figure, my estimate, flagged for argument.
A4: Key | B4: Input | C4: Value | D4: Unit | E4: Read / dated | F4: Source
B5: Top-down inputs
A6: nvda_sov_fy26 | B6: NVIDIA sovereign AI revenue, FY2026 (ended 25 Jan 2026) | C6: 30 | D6: $B | E6: 25 Feb 2026 | F6: NVIDIA Q4 FY26 earnings call as cited by State of AI Report 2026 and Fortune (15 Oct 2026, 'tripled to more than $30 billion'). https://fortune.com/2026/10/15/nvidias-european-spending-spree-is-about-much-more-than-europe/
A7: nvda_sov_growth | B7: Growth in NVIDIA sovereign revenue, FY26 to calendar 2026 | C7: 0.4 | D7: fraction | E7: My assumption | F7: It tripled in FY26. Pipeline (HUMAIN 600k GPUs, Korea 260k, Japan 27.5k Rubin, Nscale 58.6k) supports continued growth but power gates delivery. 40%. Lever.
A8: nvda_share | B8: NVIDIA share of accelerator revenue in sovereign deals | C8: 0.85 | D8: fraction | E8: 2026 | F8: Higher than the ~80% global share because sovereign deals are mostly NVIDIA-branded AI factories; AMD (HUMAIN 1 GW), Qualcomm (200 MW) and Groq (19,000 LPUs) take the rest. Lever.
A9: server_share | B9: Servers incl. GPUs as share of a data center's up-front capex | C9: 0.64 | D9: fraction | E9: Jun 2026 | F9: Carnegie Endowment, The Compute Coalition: servers 64%, networking 11%, storage 5%, engineering and construction 11%, electrical 5%, thermal 2.5%, generators 2%. https://carnegieendowment.org/research/2026/06/the-compute-coalition-how-to-build-the-future-of-ai-in-the-free-world
A10: mm_2025 | B10: Sovereign AI market, 2025 (MarketsandMarkets) | C10: 40 | D10: $B | E10: 19 Aug 2026 | F10: MarketsandMarkets press release: $40.0B (2025) to $148.0B (2032), 20.6% CAGR. https://finance.yahoo.com/technology/ai/articles/sovereign-ai-market-reach-usd-151500186.html
A11: mm_cagr | B11: Sovereign AI market CAGR 2026-2032 (MarketsandMarkets) | C11: 0.206 | D11: fraction | E11: 19 Aug 2026 | F11: Same release.
A12: gvr_2026 | B12: Sovereign AI market, 2026 (Grand View Research) | C12: 48.9 | D12: $B | E12: 2026 | F12: Grand View Research: $41.3B 2025, $48.9B 2026, $180.5B 2033, 20.5% CAGR. https://www.grandviewresearch.com/industry-analysis/sovereign-ai-market-report
A13: gvr_hw | B13: Hardware share of the sovereign AI market (Grand View) | C13: 0.48 | D13: fraction | E13: 2026 | F13: Same source (48.0% in 2025).
A14: prec_2026 | B14: Sovereign AI infrastructure market, 2026 (Precedence Research) | C14: 19.2 | D14: $B | E14: 2026 | F14: Precedence Research: $15.0B 2025, $19.2B 2026, $177.1B 2035, 28% CAGR. https://www.precedenceresearch.com/sovereign-ai-infrastructure-market
A15: sns_2025 | B15: Sovereign AI infrastructure market, 2025 (SNS Insider) | C15: 17.81 | D15: $B | E15: 2026 | F15: SNS Insider: $17.81B 2025 to $91.99B 2035. https://www.snsinsider.com/reports/sovereign-ai-infrastructure-market-10918
A16: ai_infra_26 | B16: Worldwide AI infrastructure spending, 2026 (Gartner) | C16: 1484.4 | D16: $B | E16: 16 Sep 2026 | F16: Gartner, Worldwide AI Spending to Grow 49.5% in 2026. https://www.gartner.com/en/newsroom/press-releases/2026-09-16-gartner-forecasts-worldwide-ai-spending-to-grow-49-point-5-percent-in-2026
A17: providers_2026 | B17: AI providers' AI infrastructure spend, 2026 (Gartner) | C17: 1000 | D17: $B | E17: 14 Oct 2026 | F17: Gartner: AI providers expected to spend nearly $1 trillion on AI infrastructure in 2026 and $6 trillion more 2027-2030. https://www.gartner.com/en/newsroom/press-releases/2026-10-14-gartner-says-over-us-dollars-three-and-a-half-trillion-of-artificial-intelligence-infrastructure-spending-could-be-exposed-to-impairment-by-the-end-of-2030
A18: hyper_capex | B18: Four US hyperscalers' 2026 capex guidance | C18: 733 | D18: $B | E18: Oct 2026 | F18: State of AI Report 2026 (~$733B); J.P. Morgan estimates $697B; Carnegie ~$670B. https://www.stateof.ai/
B19: Public funding commitments (Path C)
A20: eu_giga | B20: EU and national funding for AI Gigafactories | C20: 10 | D20: EUR B | E20: 12 Aug 2026 | F20: European Commission AI Factories page: up to EUR 10B EU and national funding, to unlock at least EUR 20B private; up to seven gigafactories of >100,000 processors. https://digital-strategy.ec.europa.eu/en/policies/ai-factories
A21: eu_factories | B21: EuroHPC supercomputing and AI Factories budget, 2021-2027 | C21: 10 | D21: EUR B | E21: 12 Aug 2026 | F21: Same page (EUR 10B over 2021-2027; 19 AI Factories selected).
A22: eu_years | B22: Years over which the EU money is spent | C22: 5 | D22: years | E22: My assumption | F22: 2026-2030 for gigafactories; AI Factories run 2021-2027.
A23: eur_usd | B23: EUR to USD | C23: 1.08 | D23: USD per EUR | E23: Oct 2026 | F23: Approximate 2026 rate. My figure.
A24: jp_budget | B24: Japan METI/NEDO/IPA AI and semiconductor budget, FY2026 | C24: 7.9 | D24: $B | E24: May 2026 | F24: Augur, Who Owns AI? (~JPY 1.23T). Includes Rapidus. https://whoownsai.org/who-owns-ai.pdf
A25: jp_compute_share | B25: Share of Japan's budget that is compute rather than fabs | C25: 0.4 | D25: fraction | E25: My assumption | F25: Rapidus takes the majority. METI GPU cloud subsidies were JPY 72.5B; GENIAC adds compute. 40%. Lever.
A26: jp_rubin_inv | B26: Japan Rubin consortium (Noetra) planned investment over five years | C26: 6.7 | D26: $B | E26: Jul 2026 | F26: Spheron: ~JPY 1 trillion over five years behind 27,500 Rubin GPUs. https://www.spheron.network/blog/gpu-cloud-providers-japan-2026/
A27: kr_gpus_gov | B27: Korea MSIT sovereign GPUs (National AI Computing Center and sovereign clouds) | C27: 50000 | D27: GPUs | E27: 31 Oct 2025 | F27: NVIDIA press release: up to 50,000 GPUs via MSIT, initial 13,000 Blackwell. https://investor.nvidia.com/news/press-release-details/2025/NVIDIA-South-Korea-Government-and-Industrial-Giants-Build-AI-Infrastructure-and-Ecosystem-to-Fuel-Korea-Innovation-Industries-and-Jobs/default.aspx
A28: kr_years | B28: Years over which Korea's government GPUs deploy | C28: 3 | D28: years | E28: 31 Oct 2025 | F28: Same release ('over the next several years').
A29: in_budget | B29: IndiaAI Mission public commitment over five years | C29: 1.2 | D29: $B | E29: 19 Aug 2026 | F29: MarketsandMarkets: exceeding $1B over five years. https://finance.yahoo.com/technology/ai/articles/sovereign-ai-market-reach-usd-151500186.html
A30: uk_budget | B30: UK AI compute commitments (AI and quantum package, AIRR to 2030, Sovereign AI Unit) | C30: 4.5 | D30: GBP B | E30: May 2026 | F30: Augur: GBP 2.5B AI+quantum package (Mar 2026), AIRR >GBP 1B by 2030, Sovereign AI Unit GBP 500M, GBP 80M procurement. https://whoownsai.org/who-owns-ai.pdf
A31: uk_years | B31: Years over which UK money is spent | C31: 4 | D31: years | E31: My assumption | F31: To 2030.
... A33: fr_bpi | B33: Bpifrance AI commitment by 2029 | C33: 10 | D33: EUR B | E33: Feb 2025 | F33: Augur / TechCrunch 7 Feb 2025. https://whoownsai.org/who-owns-ai.pdf
A34: fr_years | B34: Years for Bpifrance commitment | C34: 5 | D34: years | F34: 2025-2029.
A35: my_budget | B35: Malaysia 2026 budget for AI incl. sovereign AI cloud | C35: 1.41 | D35: $B | E35: 2026 | F35: Introl: MYR 5.9B ($1.41B) for AI; Digital in Asia: MYR 2.1B (~$490M) for a sovereign AI cloud. https://introl.com/blog/malaysia-thailand-emerging-ai-data-center-hubs-southeast-asia
A36: sa_nif | B36: Saudi National Infrastructure Fund financing framework for HUMAIN (250 MW) | C36: 1.2 | D36: $B | E36: 2025 | F36: Saudi Market Research Consulting summary of HUMAIN/Infra agreement (non-binding). https://saudimarketresearchconsulting.com/insights/articles/humain-saudi-arabia-a-bold-sovereign-ai-push-reshaping-infrastructure-and-markets
A37: ca_budget | B37: Canada Sovereign AI Compute Strategy | C37: 2 | D37: CAD B | E37: 2024-2025 | F37: Canadian federal budget commitment, widely reported; order of magnitude. My figure.
A38: cad_usd | B38: CAD to USD | C38: 0.73 | D38: USD per CAD | E38: Oct 2026 | F38: Approximate. My figure.
A39: ca_years | B39: Years for Canada's programme | C39: 5 | D39: years
A40: leverage | B40: Private and sovereign-wealth capital mobilised per dollar of public budget | C40: 2 | D40: x | E40: My assumption | F40: The Commission targets 10x private leverage for gigafactories; Japan's Noetra is 44 private companies behind public subsidy; Gulf capital is sovereign wealth rather than budget. 2x is deliberately conservative. Lever.
B41: Cost of a gigawatt (Epoch AI, GB200 NVL72 build, US hyperscaler)
A42: capex_gw | B42: Up-front capex for a 1 GW IT-load AI data center | C42: 38 | D42: $B | E42: 19 May 2026 | F42: Epoch AI, Total cost of ownership of a one-gigawatt AI data center. https://epoch.ai/data-insights/ai-datacenter-cost-breakdown
A43: opex_gw | B43: Annual operating cost for 1 GW | C43: 0.9 | D43: $B per year | E43: 14 May 2026 | F43: Same source ($0.9B/yr).
A44: tco_gw_yr | B44: Annualised total cost of ownership for 1 GW | C44: 8.5 | D44: $B per year | E44: 14 May 2026 | F44: Same source ($8.5B/yr; servers $5B = 60%; network $1.4B; facility $1.2B; energy $590M; labour $140M; maintenance $120M).
A45: energy_gw_yr | B45: Energy cost for 1 GW per year (US) | C45: 0.59 | D45: $B per year | E45: 14 May 2026 | F45: Same source.
A46: server_life | B46: IT equipment lifespan assumed | C46: 4 | D46: years | E46: 14 May 2026 | F46: Epoch: 3 years gives $12B/yr, 7 years gives $7B/yr; the base case implies about 4. With facility over 10 years this reproduces Epoch's $8.5B/yr within 2%.
A47: facility_life | B47: Facility, network and electrical lifespan | C47: 10 | D47: years | E47: My assumption | F47: Buildings last longer, network and electrical gear less. 10 years blended.
A48: hurdle | B48: Cost of capital applied to capex (Gartner hurdle rate) | C48: 0.12 | D48: fraction | E48: 14 Oct 2026 | F48: Gartner assumes a 12% return on invested capital as the hurdle for AI data center owners. https://www.gartner.com/en/newsroom/press-releases/2026-10-14-gartner-says-over-us-dollars-three-and-a-half-trillion-of-artificial-intelligence-infrastructure-spending-could-be-exposed-to-impairment-by-the-end-of-2030
A49: rack_kw | B49: GB200 NVL72 rack power | C49: 120 | D49: kW | E49: 2026 | F49: Widely reported; GB300 racks 135-140 kW (vision2030.ai citing Tom's Hardware). https://vision2030.ai/analysis/humain-ai-infrastructure/
A50: rack_gpus | B50: GPUs per NVL72 rack | C50: 72 | D50: GPUs
A51: gb300_rack_kw | B51: GB300 NVL72 rack power | C51: 137.5 | D51: kW | E51: 2026 | F51: 135-140 kW (vision2030.ai). Midpoint.
A52: util | B52: Utilisation of a sovereign AI factory | C52: 0.7 | D52: fraction | E52: Jun 2026 | F52: Carnegie and BloombergNEF assume ~70% (BNEF: 69% average by 2035). Lever.
A53: hours | B53: Hours per year | C53: 8760 | D53: hours
A54: us_power | B54: US industrial electricity price | C54: 0.0977 | D54: $ per kWh | E54: Jul 2026 | F54: EIA Electricity Monthly Update, end use, July 2026. https://www.eia.gov/electricity/monthly/update/end-use.php
A55: delay_1y | B55: Lifecycle value lost by a one-year delay to a US data center | C55: 0.055 | D55: fraction | E55: Jun 2026 | F55: Carnegie: >5% of total value (>$500M on a 100 MW facility); 1.5-year delay -8.9%, 6-month -3.6%, 3-month -1.7%. https://carnegieendowment.org/research/2026/06/the-compute-coalition-how-to-build-the-future-of-ai-in-the-free-world
A56: delay_cost_100mw | B56: Lifecycle value lost by a one-year delay to a 100 MW US data center | C56: 500 | D56: $M | E56: Jun 2026 | F56: Same source (more than $500 million).
A57: gb200_hr | B57: GB200 lowest on-demand rental price | C57: 10.5 | D57: $ per GPU-hour | E57: May 2026 | F57: Carnegie citing getdeploying.com (CoreWeave). Carnegie models $10.
B58: Country factors (Carnegie Compute Coalition lifecycle value index, US = 0)
A59: cf_uae | B59: Lifecycle value of a data center in UAE relative to the US, no delay | C59: 0.035 | D59: fraction | E59: Jun 2026 | F59: Carnegie Endowment, The Compute Coalition, country ranking figure. UK industrial power ~3x US; Germany has the longest timelines.
A60: cf_us | B60: Lifecycle value of a data center in United States relative to the US, no delay | C60: 0 | D60: fraction | E60: Jun 2026 | F60: Carnegie Endowment, The Compute Coalition, country ranking figure. UK industrial power ~3x US; Germany has the longest timelines.
A61: cf_fi | B61: Lifecycle value of a data center in Finland relative to the US, no delay | C61: -0.01 | D61: fraction | E61: Jun 2026 | F61: Carnegie Endowment, The Compute Coalition, country ranking figure. UK industrial power ~3x US; Germany has the longest timelines.
A62: cf_ca | B62: Lifecycle value of a data center in Canada relative to the US, no delay | C62: -0.036 | D62: fraction | E62: Jun 2026 | F62: Carnegie Endowment, The Compute Coalition, country ranking figure. UK industrial power ~3x US; Germany has the longest timelines.
A63: cf_in | B63: Lifecycle value of a data center in India relative to the US, no delay | C63: -0.048 | D63: fraction | E63: Jun 2026 | F63: Carnegie Endowment, The Compute Coalition, country ranking figure. UK industrial power ~3x US; Germany has the longest timelines.
A64: cf_fr | B64: Lifecycle value of a data center in France relative to the US, no delay | C64: -0.077 | D64: fraction | E64: Jun 2026 | F64: Carnegie Endowment, The Compute Coalition, country ranking figure. UK industrial power ~3x US; Germany has the longest timelines.
A65: cf_kr | B65: Lifecycle value of a data center in South Korea relative to the US, no delay | C65: -0.125 | D65: fraction | E65: Jun 2026 | F65: Carnegie Endowment, The Compute Coalition, country ranking figure. UK industrial power ~3x US; Germany has the longest timelines.
A66: cf_au | B66: Lifecycle value of a data center in Australia relative to the US, no delay | C66: -0.164 | D66: fraction | E66: Jun 2026 | F66: Carnegie Endowment, The Compute Coalition, country ranking figure. UK industrial power ~3x US; Germany has the longest timelines.
A67: cf_uk | B67: Lifecycle value of a data center in United Kingdom relative to the US, no delay | C67: -0.187 | D67: fraction | E67: Jun 2026 | F67: Carnegie Endowment, The Compute Coalition, country ranking figure. UK industrial power ~3x US; Germany has the longest timelines.
A68: cf_de | B68: Lifecycle value of a data center in Germany relative to the US, no delay | C68: -0.194 | D68: fraction | E68: Jun 2026 | F68: Carnegie Endowment, The Compute Coalition, country ranking figure. UK industrial power ~3x US; Germany has the longest timelines.
A69: power_sa | B69: Industrial electricity price, Saudi Arabia | C69: 0.05 | D69: $ per kWh | E69: My assumption | F69: Regulated industrial tariff plus solar PPAs at record lows (Sakaka, Al Shuaibah, Sudair cited by vision2030.ai). 5 cents. Lever.
A70: power_kr | B70: Industrial electricity price, South Korea | C70: 0.13 | D70: $ per kWh | E70: My assumption | F70: Carnegie ranks Korea -12.5% and notes prices 23% above the model band. 13 cents.
... A77: war_ins | B77: Gulf war-risk and country premium applied to data center capex per year | C77: 0.025 | D77: fraction of capex per year | E77: 1 Apr 2026 | F77: Semafor via Carnegie: Gulf war insurance rose 19x to $5M per $100M of coverage (5%) with reduced limits. Not all capex is insured at that rate. 2.5%. Lever.
B78: Pricing inputs ($ per GPU-hour, list, read Sep-Oct 2026)
A79: p_aws_eu | B79: AWS p5 H100, Stockholm | C79: 7.36 | D79: $ per GPU-hour | E79: Sep-Oct 2026 | F79: Qovery, Sep 2026 list. https://www.qovery.com/blog/european-gpu-cloud-alternatives-aws-azure-comparison
A80: p_azure_eu | B80: Azure ND H100 v5, West Europe | C80: 15.98 | D80: $ per GPU-hour | E80: Sep-Oct 2026 | F80: Qovery, Sep 2026.
A81: p_scaleway | B81: Scaleway H100 PCIe, Paris (EUR 2.87) | C81: 3.1 | D81: $ per GPU-hour | E81: Sep-Oct 2026 | F81: Qovery, Sep 2026, converted at 1.08.
A82: p_ovh | B82: OVHcloud H100, Gravelines | C82: 2.99 | D82: $ per GPU-hour | E82: Sep-Oct 2026 | F82: Qovery / Spheron, Sep-Oct 2026. https://www.spheron.network/blog/ovhcloud-gpu-pricing-2026-h100-cost-and-sovereign-ai/
A83: p_verda_b200 | B83: Verda B200, Finland | C83: 6.11 | D83: $ per GPU-hour | E83: Sep-Oct 2026 | F83: Qovery, Sep 2026.
A84: p_nebius_b200 | B84: Nebius B200 | C84: 8.5 | D84: $ per GPU-hour | E84: Sep-Oct 2026 | F84: computeprices.com, 14 Oct 2026. https://computeprices.com/providers/nebius
A85: p_nebius_h100 | B85: Nebius H100 SXM | C85: 4.5 | D85: $ per GPU-hour | E85: Sep-Oct 2026 | F85: Same.
A86: p_coreweave_h100 | B86: CoreWeave HGX H100, UK/Norway/Sweden/Spain | C86: 6.16 | D86: $ per GPU-hour | E86: Sep-Oct 2026 | F86: Qovery, Sep 2026.
A87: p_sakura | B87: Sakura Internet H100, Japan (JPY 990) | C87: 6.07 | D87: $ per GPU-hour | E87: Sep-Oct 2026 | F87: Spheron, Oct 2026. https://www.spheron.network/blog/gpu-cloud-providers-japan-2026/
A88: p_aws_jp | B88: AWS Japan H100 | C88: 12.3 | D88: $ per GPU-hour | E88: Sep-Oct 2026 | F88: Spheron, Oct 2026.
A89: p_india_sub | B89: IndiaAI subsidised high-end GPU rate (INR 150) | C89: 1.7 | D89: $ per GPU-hour | E89: Sep-Oct 2026 | F89: MeitY / IndiaAI; INR 65-150 vs INR 210-335 commercial. https://indiaai.gov.in/hub/indiaai-compute-capacity
A90: p_india_com | B90: Commercial H100 rate in India (INR 300 midpoint) | C90: 3.4 | D90: $ per GPU-hour | E90: Sep-Oct 2026 | F90: Fundingsstartup summary of IndiaAI comparison.
... A93: gb300_chip | B93: GB300 chip value implied by US export approvals | C93: 28571 | D93: $ per chip | E93: Nov 2025 | F93: vision2030.ai: 35,000 GB300-equivalent chips estimated at ~$1B, i.e. ~$28.6k each. Street B300 ~$53k (tech-insider). The gap is the allocation-price vs street-price spread.
B94: Value inputs
A95: pwc_gdp | B95: AI contribution to global GDP by 2030 (PwC) | C95: 15.7 | D95: $T | E95: 2017 | F95: PwC Sizing the Prize, via WEF. https://www.weforum.org/stories/geographies-in-depth/the-global-economy-will-be-14-bigger-in-2030-because-of-ai
A96: pwc_pct | B96: GDP uplift by 2030 (PwC) | C96: 0.14 | D96: fraction | E96: 2017 | F96: Same.
A97: idc_gdp | B97: Cumulative AI economic impact through 2030 (IDC) | C97: 19.9 | D97: $T | E97: 2024 | F97: IDC: $19.9T, 3.5% of global GDP in 2030. https://my.idc.com/getdoc.jsp?containerId=prUS52600524
A98: th_value | B98: Economic value of Google's Bangkok cloud region over five years | C98: 41 | D98: $B | E98: 21 Jan 2026 | F98: Google Cloud / Public First: THB 1.4T. https://www.googlecloudpresscorner.com/2026-01-21-Google-Cloud-Launches-New-Cloud-Region-in-Thailand,-Bolstering-its-Commitment-to-Advancing-the-Countrys-AI-Driven-Digital-Economy
A99: th_invest | B99: Google's Thailand investment behind it | C99: 1 | D99: $B | E99: 21 Jan 2026 | F99: Same.
A100: anthropic_ratio | B100: Frontier lab revenue per dollar of compute | C100: 1.7 | D100: $ revenue per $ compute | E100: 15 Oct 2026 | F100: Fortune: Anthropic told investors $1.70 of revenue per $1 of compute; Q3 revenue $16.8B. https://fortune.com/2026/10/15/nvidias-european-spending-spree-is-about-much-more-than-europe/
A101: gartner_rev_need | B101: Cumulative revenue AI data center owners need through 2030 (Gartner) | C101: 8.5 | D101: $T | E101: 14 Oct 2026 | F101: Gartner: to cover capex, financing and 12% ROIC. https://www.gartner.com/en/newsroom/press-releases/2026-10-14-gartner-says-over-us-dollars-three-and-a-half-trillion-of-artificial-intelligence-infrastructure-spending-could-be-exposed-to-impairment-by-the-end-of-2030
A102: gartner_rev_have | B102: AI revenue attributable to AI data centers through 2030 (Gartner) | C102: 3.6 | D102: $T | E102: 14 Oct 2026 | F102: Same (no more than $3.6T).
A103: gartner_impair | B103: AI infrastructure exposed to impairment by end-2030 (Gartner) | C103: 3.5 | D103: $T | E103: 14 Oct 2026 | F103: Same (>$3.5T; >$4T through 2032; 80% of neoclouds cease independent operation by 2030).
A104: gdp_sa | B104: Saudi Arabia GDP | C104: 1.1 | D104: $T | E104: 2025 | F104: Approximate nominal GDP. My figure.
A105: gdp_kr | B105: South Korea GDP | C105: 1.8 | D105: $T | E105: 2025 | F105: Approximate. My figure.
A106: gdp_eu | B106: EU GDP | C106: 19 | D106: $T | E106: 2025 | F106: Approximate. My figure.
... A109: ai_share_gdp | B109: Share of PwC's AI GDP uplift that depends on in-country compute (vs imported services) | C109: 0.25 | D109: fraction | E109: My assumption | F109: Most AI value is consumed as software and services that can run anywhere. Sovereign compute captures the part that must be local (regulated data, defence, latency, language). 25%. Lever.

Sheet BottomUp
A1: Bottom-up: sovereign AI compute programmes, capacity announced and energised in 2026
A2: MW are IT load. Energised-in-2026 is my estimate from each programme's disclosed phases. Capex per MW from Epoch ($38B/GW). GPUs per MW from NVL72 rack density. $M unless noted.
A4: Programme | B4: Quadrant | C4: Country | D4: Announced MW (IT) | E4: Target year | F4: MW energised by end-2026 | G4: GPUs announced | H4: GPUs implied in 2026 (MW x GPUs/MW) | I4: Capex energised 2026 ($M) | J4: Of which GPU systems ($M) | K4: Announced capex to target ($B) | L4: Source note
A5: HUMAIN (PIF) AI factories incl. xAI 500 MW+, AMD 1 GW, stc 1 GW | B5: Compute exporters | C5: Saudi Arabia | D5: 1900 | E5: 2030 | F5: 150 | G5: 600000 | H5: =F5*1000/Assumptions!$C$49*Assumptions!$C$50 -> 90000 | I5: =F5*Assumptions!$C$42 -> 5700 | J5: =I5*Assumptions!$C$9 -> 3648 | K5: =D5*Assumptions!$C$42/1000 -> 72.2 | L5: 1.9 GW by 2030, 6.6 GW by 2034; 50 MW pilot with 18,000 GB300 live 2026; AMD first 100 MW phase 2026. vision2030.ai; Saudi MRC.
A6: Stargate UAE (G42, OpenAI, Oracle) within 5 GW campus | B6: Compute exporters | C6: UAE | D6: 1000 | E6: 2029 | F6: 200 | G6: 0 | H6: =F6*1000/Assumptions!$C$49*Assumptions!$C$50 -> 120000 | I6: =F6*Assumptions!$C$42 -> 7600 | J6: =I6*Assumptions!$C$9 -> 4864 | K6: =D6*Assumptions!$C$42/1000 -> 38 | L6: 1 GW first phase ~$20B; 200 MW live 2026 (OpenAI, G42, Zawya).
A7: AWS Riyadh AI Zone (HUMAIN) and other Gulf (Qatar, QIA-Brookfield $20B JV) | B7: Compute exporters | C7: Gulf other | D7: 400 | E7: 2029 | F7: 40 | G7: 150000 | H7: =F7*1000/Assumptions!$C$49*Assumptions!$C$50 -> 24000 | I7: =F7*Assumptions!$C$42 -> 1520 | J7: =I7*Assumptions!$C$9 -> 972.8 | K7: =D7*Assumptions!$C$42/1000 -> 15.2 | L7: AWS up to 150,000 accelerators in Riyadh, 100 MW with gigawatt ambition; QIA-Brookfield JV. My capacity estimate.
A8: Korea sovereign GPUs: MSIT 50k, SK 50k, Hyundai 50k, NAVER 60k | B8: Industrial sovereigns | C8: South Korea | D8: 500 | E8: 2028 | F8: 110 | G8: 260000 | H8: =F8*1000/Assumptions!$C$49*Assumptions!$C$50 -> 66000 | I8: =F8*Assumptions!$C$42 -> 4180 | J8: =I8*Assumptions!$C$9 -> 2675.2 | K8: =D8*Assumptions!$C$42/1000 -> 19 | L8: NVIDIA release 31 Oct 2025: >260,000 GPUs. MW derived at ~1.9 kW per GPU installed.
A9: Japan: Noetra 27,500 Rubin, SoftBank GB200 cloud, Sakura 22k GPUs, METI JPY 72.5B subsidies | B9: Industrial sovereigns | C9: Japan | D9: 200 | E9: 2028 | F9: 40 | G9: 60000 | H9: =F9*1000/Assumptions!$C$49*Assumptions!$C$50 -> 24000 | I9: =F9*Assumptions!$C$42 -> 1520 | J9: =I9*Assumptions!$C$9 -> 972.8 | K9: =D9*Assumptions!$C$42/1000 -> 7.6 | L9: Spheron Oct 2026; GPU count sums Rubin 27.5k, Sakura ~21k, SoftBank est. 10k.
A10: Taiwan NT$100B AI initiative and national AI supercomputer | B10: Industrial sovereigns | C10: Taiwan | D10: 60 | E10: 2027 | F10: 20 | G10: 10000 | H10: =F10*1000/Assumptions!$C$49*Assumptions!$C$50 -> 12000 | I10: =F10*Assumptions!$C$42 -> 760 | J10: =I10*Assumptions!$C$9 -> 486.4 | K10: =D10*Assumptions!$C$42/1000 -> 2.28 | L10: Augur (Jun 2025 initiative). ~10,000 Blackwell class. My MW estimate.
A11: EU AI Gigafactories (up to 7 x 100,000 processors) | B11: Regulated builders | C11: EU | D11: 1400 | E11: 2030 | F11: 0 | G11: 500000 | H11: =F11*1000/Assumptions!$C$49*Assumptions!$C$50 -> 0 | I11: =F11*Assumptions!$C$42 -> 0 | J11: =I11*Assumptions!$C$9 -> 0 | K11: =D11*Assumptions!$C$42/1000 -> 53.2 | L11: EC: tenders launched Aug 2026; EUR 10B public to unlock EUR 20B private. Nothing energised in 2026. 5 x 100k chips x ~2 kW.
A12: EuroHPC AI Factories (19 selected, first 6 live Oct 2025) | B12: Regulated builders | C12: EU | D12: 300 | E12: 2027 | F12: 120 | G12: 60000 | H12: =F12*1000/Assumptions!$C$49*Assumptions!$C$50 -> 72000 | I12: =F12*Assumptions!$C$42 -> 4560 | J12: =I12*Assumptions!$C$9 -> 2918.4 | K12: =D12*Assumptions!$C$42/1000 -> 11.4 | L12: EC; Augur. ~15 MW average each. My estimate.
A13: France: AI Campus JV 1.4 GW (ops 2028), Mistral Compute 40 MW (18,000 GB chips), UAE-France 1 GW | B13: Regulated builders | C13: France | D13: 2400 | E13: 2030 | F13: 60 | G13: 18000 | H13: =F13*1000/Assumptions!$C$49*Assumptions!$C$50 -> 36000 | I13: =F13*Assumptions!$C$42 -> 2280 | J13: =I13*Assumptions!$C$9 -> 1459.2 | K13: =D13*Assumptions!$C$42/1000 -> 91.2 | L13: Augur; Mistral Compute 40 MW live 2026 + early campus works.
A14: Germany: Deutsche Telekom Industrial AI Cloud, 10,000 Blackwell GPUs, Munich | B14: Regulated builders | C14: Germany | D14: 25 | E14: 2026 | F14: 25 | G14: 10000 | H14: =F14*1000/Assumptions!$C$49*Assumptions!$C$50 -> 15000 | I14: =F14*Assumptions!$C$42 -> 950 | J14: =I14*Assumptions!$C$9 -> 608 | K14: =D14*Assumptions!$C$42/1000 -> 0.95 | L14: Telekom 4 Nov 2025; live Q1 2026; >1,000 DGX B200 at 14.3 kW.
A15: UK: Nscale 58,640 GPUs incl. Loughton 50-90 MW (Q1 2027), Stargate UK, Isambard, AIRR | B15: Regulated builders | C15: UK | D15: 200 | E15: 2028 | F15: 30 | G15: 58640 | H15: =F15*1000/Assumptions!$C$49*Assumptions!$C$50 -> 18000 | I15: =F15*Assumptions!$C$42 -> 1140 | J15: =I15*Assumptions!$C$9 -> 729.6 | K15: =D15*Assumptions!$C$42/1000 -> 7.6 | L15: Nscale 16 Sep 2025; OpenAI Stargate UK. Loughton delivers Q1 2027.
A16: Nordics and other EU national (Denmark Gefion, Italy, Spain, Switzerland Alps, Norway) | B16: Regulated builders | C16: Europe other | D16: 150 | E16: 2028 | F16: 50 | G16: 30000 | H16: =F16*1000/Assumptions!$C$49*Assumptions!$C$50 -> 30000 | I16: =F16*Assumptions!$C$42 -> 1900 | J16: =I16*Assumptions!$C$9 -> 1216 | K16: =D16*Assumptions!$C$42/1000 -> 5.7 | L16: My estimate of national supercomputer and sovereign cloud builds.
... A22: Latin America (Brazil, Mexico, Chile) sovereign and national supercomputers | B22: Subsidised tenants | C22: LatAm | D22: 80 | E22: 2029 | F22: 20 | G22: 0 | H22: =F22*1000/Assumptions!$C$49*Assumptions!$C$50 -> 12000 | I22: =F22*Assumptions!$C$42 -> 760 | J22: =I22*Assumptions!$C$9 -> 486.4 | K22: =D22*Assumptions!$C$42/1000 -> 3.04 | L22: My estimate.
A23: Total | D23: =SUM(D5:D22) -> 10005 | F23: =SUM(F5:F22) -> 1125 | G23: =SUM(G5:G22) -> 1801640 | H23: =SUM(H5:H22) -> 675000 | I23: =SUM(I5:I22) -> 42750 | J23: =SUM(J5:J22) -> 27360 | K23: =SUM(K5:K22) -> 380.19
A25: Formulas. GPUs implied 2026 = MW energised x 1,000 / rack kW x 72 GPUs per rack. Capex energised = MW x $38M per MW (Epoch, $38B per GW, all-in incl. facility). GPU systems = capex x 64% server share (Carnegie). Announced capex = announced MW x $38M.
A27: By quadrant, 2026
A28: Quadrant | B28: MW energised 2026 | C28: GPUs implied 2026 | D28: Capex energised 2026 ($M) | E28: GPU systems 2026 ($M) | F28: Announced MW
A29: Compute exporters | B29: =SUMIF($B$5:$B$22,A29,$F$5:$F$22) -> 390 | C29: =SUMIF($B$5:$B$22,A29,$H$5:$H$22) -> 234000 | D29: =SUMIF($B$5:$B$22,A29,$I$5:$I$22) -> 14820 | E29: =SUMIF($B$5:$B$22,A29,$J$5:$J$22) -> 9484.8 | F29: =SUMIF($B$5:$B$22,A29,$D$5:$D$22) -> 3300
A30: Industrial sovereigns | B30: =SUMIF($B$5:$B$22,A30,$F$5:$F$22) -> 170 | C30: =SUMIF($B$5:$B$22,A30,$H$5:$H$22) -> 102000 | D30: =SUMIF($B$5:$B$22,A30,$I$5:$I$22) -> 6460 | E30: =SUMIF($B$5:$B$22,A30,$J$5:$J$22) -> 4134.4 | F30: =SUMIF($B$5:$B$22,A30,$D$5:$D$22) -> 760
A31: Regulated builders | B31: =SUMIF($B$5:$B$22,A31,$F$5:$F$22) -> 285 | C31: =SUMIF($B$5:$B$22,A31,$H$5:$H$22) -> 171000 | D31: =SUMIF($B$5:$B$22,A31,$I$5:$I$22) -> 10830 | E31: =SUMIF($B$5:$B$22,A31,$J$5:$J$22) -> 6931.2 | F31: =SUMIF($B$5:$B$22,A31,$D$5:$D$22) -> 4475
A32: Subsidised tenants | B32: =SUMIF($B$5:$B$22,A32,$F$5:$F$22) -> 280 | C32: =SUMIF($B$5:$B$22,A32,$H$5:$H$22) -> 168000 | D32: =SUMIF($B$5:$B$22,A32,$I$5:$I$22) -> 10640 | E32: =SUMIF($B$5:$B$22,A32,$J$5:$J$22) -> 6809.6 | F32: =SUMIF($B$5:$B$22,A32,$D$5:$D$22) -> 1470
A33: Share of 2026 capex in the Gulf | D33: =D29/I23 -> 0.34666667
A34: Share of announced MW in Europe (Regulated builders) | F34: =F31/D23 -> 0.44727636
A35: Europe share of 2026 energised MW | B35: =B31/F23 -> 0.25333333
A37: Summary 2026
A38: MW energised 2026 (GW) | C38: =F23/1000 -> 1.125
A39: Sovereign AI capex energised 2026, all-in ($B) | C39: =I23/1000 -> 42.75
A40: Of which GPU systems ($B) | C40: =J23/1000 -> 27.36
A41: GPUs implied by 2026 energisation | C41: =H23 -> 675000
A42: Announced pipeline, all programmes (GW) | C42: =D23/1000 -> 10.005
A43: Announced pipeline capex ($B) | C43: =K23 -> 380.19
A44: Years to deliver pipeline at 2026 pace | C44: =D23/F23 -> 8.8933333 | D44: Announced MW / MW energised in 2026. Shows how far announcements run ahead of delivery.

Sheet TopDown
A1: Top-down: three paths to 2026 sovereign AI compute spend
A2: $B. Path A grosses up NVIDIA's disclosed sovereign revenue to all vendors and to the full data center. Path B uses analyst market estimates. Path C starts from public budgets and applies leverage.
A4: Line | B4: Item | C4: Value | D4: Formula (in words) and source
B5: Path A: from NVIDIA's disclosed sovereign AI revenue
A6: A1 | B6: NVIDIA sovereign AI revenue, FY2026 | C6: =Assumptions!$C$6 -> 30 | D6: >$30B, tripled year on year.
A7: A2 | B7: Growth to calendar 2026 | C7: =Assumptions!$C$7 -> 0.4 | D7: Assumption 40%.
A8: A3 | B8: NVIDIA sovereign AI revenue, 2026 | C8: =C6*(1+C7) -> 42 | D8: A1 x (1 + A2).
A9: A4 | B9: NVIDIA share of sovereign accelerator spend | C9: =Assumptions!$C$8 -> 0.85 | D9: Assumption 85%.
A10: A5 | B10: All-vendor accelerator and system spend by sovereigns, 2026 | C10: =C8/C9 -> 49.411765 | D10: A3 / A4.
A11: A6 | B11: Server share of data center capex | C11: =Assumptions!$C$9 -> 0.64 | D11: Carnegie: 64%.
A12: A7 | B12: Sovereign AI data center capex, all-in, 2026 (Path A) | C12: =C10/C11 -> 77.205882 | D12: A5 / A6. Grosses GPU systems up to the whole facility (network, storage, building, power).
A13: A8 | B13: Implied gigawatts energised at Epoch's $38B per GW | C13: =C12/Assumptions!$C$42 -> 2.0317337 | D13: A7 / $38B. Note NVIDIA books revenue when systems ship, often a year before power is live.
B14: Path B: from analyst market estimates
A15: B1 | B15: Sovereign AI market, 2026 (MarketsandMarkets, grown from 2025) | C15: =Assumptions!$C$10*(1+Assumptions!$C$11) -> 48.24 | D15: $40.0B x 1.206.
A16: B2 | B16: Sovereign AI market, 2026 (Grand View Research) | C16: =Assumptions!$C$12 -> 48.9 | D16: $48.9B.
A17: B3 | B17: Hardware share | C17: =Assumptions!$C$13 -> 0.48 | D17: 48%.
A18: B4 | B18: Sovereign AI hardware, 2026, average of B1 and B2 times B3 | C18: =AVERAGE(C15,C16)*C17 -> 23.3136 | D18: AVERAGE(B1, B2) x B3.
A19: B5 | B19: Sovereign AI infrastructure, 2026 (Precedence Research) | C19: =Assumptions!$C$14 -> 19.2 | D19: $19.2B. Narrower definition: national data centers and government AI cloud.
A20: B6 | B20: Sovereign AI infrastructure, 2026 (SNS Insider, grown at its own CAGR) | C20: =Assumptions!$C$15*(91.99/17.81)^(1/10) -> 20.988026 | D20: $17.81B x ten-year CAGR implied by $91.99B in 2035.
A21: B7 | B21: Path B: average of the three infrastructure figures (B4, B5, B6) | C21: =AVERAGE(C18,C19,C20) -> 21.167209 | D21: AVERAGE(B4, B5, B6). Analyst definitions differ; hardware-only in B4, infrastructure incl. cloud in B5 and B6.
B22: Path C: from public budgets with private leverage
A23: C1 | B23: EU gigafactories and AI Factories, annualised ($B) | C23: =(Assumptions!$C$20+Assumptions!$C$21)/Assumptions!$C$22*Assumptions!$C$23 -> 4.32 | D23: (EUR 10B + EUR 10B) / 5 years x 1.08.
A24: C2 | B24: Japan compute budget plus Noetra, annualised ($B) | C24: =Assumptions!$C$24*Assumptions!$C$25+Assumptions!$C$26/5 -> 4.5 | D24: $7.9B x 40% + $6.7B / 5.
A25: C3 | B25: Korea government GPUs, annualised ($B) | C25: =Assumptions!$C$27*Assumptions!$C$93*2/Assumptions!$C$28/1000000000 -> 0.95236667 | D25: 50,000 GPUs x ~$28.6k chip x 2 (system) / 3 years. Industrial fleets (SK, Hyundai, NAVER) are private and enter through leverage.
A26: C4 | B26: India, UK, France, Malaysia, Saudi NIF, Canada, annualised ($B) | C26: =Assumptions!$C$29/5+Assumptions!$C$30*Assumptions!$C$32/Assumptions!$C$31+Assumptions!$C$33*Assumptions!$C$23/Assumptions!$C$34+Assumptions!$C$35+Assumptions!$C$36+Assumptions!$C$37*Assumptions!$C$38/Assumptions!$C$39 -> 6.7645 | D26: Each programme's budget divided by its years, converted to USD.
A27: C5 | B27: Public AI compute budgets, 2026 | C27: =C23+C24+C25+C26 -> 16.536867 | D27: C1 + C2 + C3 + C4. Excludes Gulf sovereign wealth, which is equity rather than budget.
A28: C6 | B28: Private and sovereign-wealth capital per public dollar | C28: =Assumptions!$C$40 -> 2 | D28: Assumption 2x (Commission targets 10x).
A29: C7 | B29: Sovereign AI compute spend, 2026 (Path C) | C29: =C27*(1+C28) -> 49.6106 | D29: C5 x (1 + C6).
B30: Reconciliation
A31: R1 | B31: Path A: NVIDIA sovereign revenue grossed up to the data center | C31: =C12 -> 77.205882
A32: R2 | B32: Path B: analyst infrastructure estimates | C32: =C21 -> 21.167209
A33: R3 | B33: Path C: public budgets with leverage | C33: =C29 -> 49.6106
A34: R4 | B34: Average of the three paths | C34: =AVERAGE(C31,C32,C33) -> 49.327897 | D34: AVERAGE(R1:R3).
A35: R5 | B35: Spread (max minus min) over average | C35: =(MAX(C31,C32,C33)-MIN(C31,C32,C33))/C34 -> 1.1360443
A36: R6 | B36: Bottom-up: capex energised in 2026, all-in | C36: =BottomUp!$C$39 -> 42.75 | D36: From BottomUp summary.
A37: R7 | B37: Bottom-up as share of top-down average | C37: =C36/C34 -> 0.86664956 | D37: R6 / R4.
A38: R8 | B38: Bottom-up gigawatts energised 2026 | C38: =BottomUp!$C$38 -> 1.125
A39: R9 | B39: Path A implied gigawatts (A8) over bottom-up gigawatts | C39: =C13/C38 -> 1.8059856 | D39: A8 / R8. Above 1.0 means NVIDIA is shipping ahead of the power being ready, i.e. GPUs sit in warehouses or on racks waiting for grid connection.
A40: R10 | B40: Sovereign share of AI providers' $1T infrastructure spend | C40: =C34/Assumptions!$C$17 -> 0.049327897 | D40: R4 / $1,000B.
A41: R11 | B41: Sovereign share of NVIDIA Data Center run-rate (A3 / annualised Q2 FY27 $89B) | C41: =C8/(89*4) -> 0.11797753 | D41: A3 / $356B.

Sheet GigawattTCO
A1: What a gigawatt costs to own, by country
A2: Epoch's US hyperscaler model, then adjusted for power price, PUE, delay and insurance. Owner's effective $ per GPU-hour at the bottom. $B unless noted.
A4: Line | B4: Item | C4: United States | D4: Saudi Arabia | E4: South Korea | F4: Germany | G4: India | H4: Formula (in words)
B5: Inputs by country
A6: G1 | B6: Industrial power price ($/kWh) | C6: =Assumptions!$C$54 -> 0.0977 | D6: =Assumptions!$C$69 -> 0.05 | E6: =Assumptions!$C$70 -> 0.13 | F6: =Assumptions!$C$71 -> 0.18 | G6: =Assumptions!$C$72 -> 0.09 | H6: From Assumptions.
A7: G2 | B7: PUE | C7: 1.2 | D7: =Assumptions!$C$74 -> 1.25 | E7: =Assumptions!$C$75 -> 1.2 | F7: =Assumptions!$C$75 -> 1.2 | G7: 1.3 | H7: US and India my figures; others from Assumptions.
A8: G3 | B8: Extra years to energise vs US | C8: 0 | D8: 0 | E8: 0.5 | F8: =Assumptions!$C$76 -> 1.5 | G8: 1 | H8: Carnegie timelines: Gulf fastest, Germany slowest. Korea and India my figures.
A9: G4 | B9: Insurance and country-risk premium (share of capex per year) | C9: 0.005 | D9: =Assumptions!$C$77 -> 0.025 | E9: 0.005 | F9: 0.005 | G9: 0.01 | H9: Gulf war-risk insurance 5% after April 2026 (Semafor); others nominal.
A10: G5 | B10: Carnegie lifecycle value index vs US (reference only) | C10: =Assumptions!$C$60 -> 0 | D10: =Assumptions!$C$59 -> 0.035 | E10: =Assumptions!$C$65 -> -0.125 | F10: =Assumptions!$C$68 -> -0.194 | G10: =Assumptions!$C$63 -> -0.048 | H10: Saudi uses the UAE figure. Independent check on the rows below.
B11: Cost of 1 GW IT load, $B
A12: G6 | B12: Up-front capex (Epoch, same hardware everywhere) | C12: =Assumptions!$C$42 -> 38 | D12: =Assumptions!$C$42 -> 38 | E12: =Assumptions!$C$42 -> 38 | F12: =Assumptions!$C$42 -> 38 | G12: =Assumptions!$C$42 -> 38 | H12: $38B. GPUs are priced the same worldwide (Carnegie), so capex barely moves by country.
A13: G7 | B13: Energy per year | C13: =1000000*C7*Assumptions!$C$53*Assumptions!$C$52*C6/1000000000 -> 0.71891568 | D13: =1000000*D7*Assumptions!$C$53*Assumptions!$C$52*D6/1000000000 -> 0.38325 | E13: =1000000*E7*Assumptions!$C$53*Assumptions!$C$52*E6/1000000000 -> 0.956592 | F13: =1000000*F7*Assumptions!$C$53*Assumptions!$C$52*F6/1000000000 -> 1.324512 | G13: =1000000*G7*Assumptions!$C$53*Assumptions!$C$52*G6/1000000000 -> 0.717444 | H13: 1,000,000 kW x PUE x 8,760 h x utilisation x $/kWh / 1e9. Epoch's US figure is $0.59B at full load.
A14: G8 | B14: Other operating cost per year (Epoch opex less energy) | C14: =Assumptions!$C$43-Assumptions!$C$45 -> 0.31 | D14: =Assumptions!$C$43-Assumptions!$C$45 -> 0.31 | E14: =Assumptions!$C$43-Assumptions!$C$45 -> 0.31 | F14: =Assumptions!$C$43-Assumptions!$C$45 -> 0.31 | G14: =Assumptions!$C$43-Assumptions!$C$45 -> 0.31 | H14: $0.9B - $0.59B = $0.31B (labour, maintenance, taxes, water).
A15: G9 | B15: Insurance and risk per year | C15: =C12*C9 -> 0.19 | D15: =D12*D9 -> 0.95 | E15: =E12*E9 -> 0.19 | F15: =F12*F9 -> 0.19 | G15: =G12*G9 -> 0.38 | H15: G6 x G4.
A16: G10 | B16: Annualised capex (servers over IT life, rest over 15 years) | C16: =C12*Assumptions!$C$9/Assumptions!$C$46+C12*(1-Assumptions!$C$9)/Assumptions!$C$47 -> 7.448 | D16: =D12*Assumptions!$C$9/Assumptions!$C$46+D12*(1-Assumptions!$C$9)/Assumptions!$C$47 -> 7.448 | E16: =E12*Assumptions!$C$9/Assumptions!$C$46+E12*(1-Assumptions!$C$9)/Assumptions!$C$47 -> 7.448 | F16: =F12*Assumptions!$C$9/Assumptions!$C$46+F12*(1-Assumptions!$C$9)/Assumptions!$C$47 -> 7.448 | G16: =G12*Assumptions!$C$9/Assumptions!$C$46+G12*(1-Assumptions!$C$9)/Assumptions!$C$47 -> 7.448 | H16: Capex x 64% / 4 years + capex x 36% / 10 years. Epoch's own annualisation gives $7.6B of capex-related cost per year.
A17: G11 | B17: Annual total cost of ownership | C17: =C16+C13+C14+C15 -> 8.6669157 | D17: =D16+D13+D14+D15 -> 9.09125 | E17: =E16+E13+E14+E15 -> 8.904592 | F17: =F16+F13+F14+F15 -> 9.272512 | G17: =G16+G13+G14+G15 -> 8.855444 | H17: G10 + G7 + G8 + G9. Epoch's US figure is $8.5B.
A18: G12 | B18: Lifecycle value lost to delay (share) | C18: =C8*Assumptions!$C$55 -> 0 | D18: =D8*Assumptions!$C$55 -> 0 | E18: =E8*Assumptions!$C$55 -> 0.0275 | F18: =F8*Assumptions!$C$55 -> 0.0825 | G18: =G8*Assumptions!$C$55 -> 0.055 | H18: Extra years x 5.5% per year (Carnegie, linearised). A 1.5-year German delay costs more than doubling its power price.
A19: G13 | B19: Delay cost, $B over a 10-year life (share x 10 x TCO) | C19: =C18*10*C17 -> 0 | D19: =D18*10*D17 -> 0 | E19: =E18*10*E17 -> 2.4487628 | F19: =F18*10*F17 -> 7.6498224 | G19: =G18*10*G17 -> 4.8704942 | H19: G12 x 10 years x G11.
A20: G14 | B20: Energy as share of annual TCO | C20: =C13/C17 -> 0.082949426 | D20: =D13/D17 -> 0.042155919 | E20: =E13/E17 -> 0.10742682 | F20: =F13/F17 -> 0.14284285 | G20: =G13/G17 -> 0.081017282 | H20: G7 / G11. Even in Germany, energy is a minority of cost. Time to power matters more than the price of power.
B21: Owner's unit economics
A22: G15 | B22: GPUs in 1 GW at NVL72 density | C22: =1000000/Assumptions!$C$49*Assumptions!$C$50 -> 600000 | D22: =1000000/Assumptions!$C$49*Assumptions!$C$50 -> 600000 | E22: =1000000/Assumptions!$C$49*Assumptions!$C$50 -> 600000 | F22: =1000000/Assumptions!$C$49*Assumptions!$C$50 -> 600000 | G22: =1000000/Assumptions!$C$49*Assumptions!$C$50 -> 600000 | H22: 1,000,000 kW / 120 kW x 72.
A23: G16 | B23: Used GPU-hours per year | C23: =C22*Assumptions!$C$53*Assumptions!$C$52 -> 3679200000 | D23: =D22*Assumptions!$C$53*Assumptions!$C$52 -> 3679200000 | E23: =E22*Assumptions!$C$53*Assumptions!$C$52 -> 3679200000 | F23: =F22*Assumptions!$C$53*Assumptions!$C$52 -> 3679200000 | G23: =G22*Assumptions!$C$53*Assumptions!$C$52 -> 3679200000 | H23: G15 x 8,760 x 70%.
A24: G17 | B24: Owner's effective cost per used GPU-hour | C24: =C17*1000000000/C23 -> 2.3556522 | D24: =D17*1000000000/D23 -> 2.4709855 | E24: =E17*1000000000/E23 -> 2.4202522 | F24: =F17*1000000000/F23 -> 2.5202522 | G24: =G17*1000000000/G23 -> 2.4068939 | H24: G11 x 1e9 / G16.
A25: G18 | B25: Same, including delay cost spread over 10 years | C25: =(C17+C19/10)*1000000000/C23 -> 2.3556522 | D25: =(D17+D19/10)*1000000000/D23 -> 2.4709855 | E25: =(E17+E19/10)*1000000000/E23 -> 2.4868092 | F25: =(F17+F19/10)*1000000000/F23 -> 2.728173 | G25: =(G17+G19/10)*1000000000/G23 -> 2.5392731 | H25: (G11 + G13 / 10) x 1e9 / G16.
A26: G18b | B26: Cost of capital on capex per year (12% hurdle), $B | C26: =C12*Assumptions!$C$48 -> 4.56 | D26: =D12*Assumptions!$C$48 -> 4.56 | E26: =E12*Assumptions!$C$48 -> 4.56 | F26: =F12*Assumptions!$C$48 -> 4.56 | G26: =G12*Assumptions!$C$48 -> 4.56 | H26: G6 x 12%. What the owner must earn above TCO to justify the capital.
A27: G18c | B27: Cost per used GPU-hour incl. 12% cost of capital | C27: =(C17+C26)*1000000000/C23 -> 3.5950521 | D27: =(D17+D26)*1000000000/D23 -> 3.7103854 | E27: =(E17+E26)*1000000000/E23 -> 3.6596521 | F27: =(F17+F26)*1000000000/F23 -> 3.7596521 | G27: =(G17+G26)*1000000000/G23 -> 3.6462938 | H27: (G11 + G18b) x 1e9 / G16. The break-even rental price for a financed owner.
A28: G19 | B28: Owner's cost as share of GB200 on-demand rental ($10.50) | C28: =C24/Assumptions!$C$57 -> 0.22434783 | D28: =D24/Assumptions!$C$57 -> 0.23533196 | E28: =E24/Assumptions!$C$57 -> 0.23050021 | F28: =F24/Assumptions!$C$57 -> 0.24002402 | G28: =G24/Assumptions!$C$57 -> 0.22922799 | H28: G17 / $10.50 (CoreWeave, May 2026).
A29: G20 | B29: Owner's cost as share of Nebius B200 ($8.50) | C29: =C24/Assumptions!$C$84 -> 0.27713556 | D29: =D24/Assumptions!$C$84 -> 0.29070418 | E29: =E24/Assumptions!$C$84 -> 0.28473556 | F29: =F24/Assumptions!$C$84 -> 0.29650026 | G29: =G24/Assumptions!$C$84 -> 0.28316399 | H29: G17 / $8.50.
A30: G21 | B30: Capex per GPU, all-in ($) | C30: =C12*1000000000/C22 -> 63333.333 | D30: =D12*1000000000/D22 -> 63333.333 | E30: =E12*1000000000/E22 -> 63333.333 | F30: =F12*1000000000/F22 -> 63333.333 | G30: =G12*1000000000/G22 -> 63333.333 | H30: G6 x 1e9 / G15. Compare the GB300 export-approval value of ~$28.6k per chip and street B300 ~$53k.

Sheet Configs
A1: Four reference configurations, one per quadrant
A2: Specified and costed on the GigawattTCO rates. Columns are comparable.
A4: Line | B4: Item | C4: Compute exporter campus | D4: Industrial AI factory | E4: EU gigafactory | F4: Subsidised national GPU pool
B5: Who builds it | C5: HUMAIN with xAI, G42 with OpenAI and Oracle | D5: Hyundai, SK, SoftBank's Noetra, Deutsche Telekom | E5: EuroHPC consortium under InvestAI | F5: IndiaAI, Malaysia sovereign cloud, Thailand
B6: Specification
A7: K1 | B7: IT load, MW | C7: 500 | D7: 100 | E7: 190 | F7: 20
A8: K2 | B8: Rack type (kW) | C8: =Assumptions!$C$51 -> 137.5 | D8: =Assumptions!$C$49 -> 120 | E8: =Assumptions!$C$49 -> 120 | F8: 14.3
A9: K3 | B9: GPUs per rack or node | C9: 72 | D9: 72 | E9: 72 | F9: 8
A10: K4 | B10: GPUs | C10: =C7*1000/C8*C9 -> 261818.18 | D10: =D7*1000/D8*D9 -> 60000 | E10: =E7*1000/E8*E9 -> 114000 | F10: =F7*1000/F8*F9 -> 11188.811
A11: K5 | B11: Cooling | C11: Liquid, closed loop | D11: Liquid | E11: Liquid | F11: Air
A12: K6 | B12: Power source | C12: Grid plus dedicated gas and solar PPAs | D12: Grid, 13c industrial | E12: Grid, 18c, 1.5-year interconnect queue | F12: Grid, 9c
A13: K7 | B13: Who pays | C13: Sovereign wealth fund equity plus project debt | D13: Chaebol or telco balance sheet with state subsidy | E13: EU and national budgets plus EIB, 10x private leverage target | F13: State budget subsidises the hour; hyperscaler or neocloud builds
A14: K8 | B14: Anchor customer | C14: xAI, OpenAI, foreign AI labs renting capacity | D14: Own group companies: automotive, semis, robotics | E14: Mistral, Black Forest Labs, Helsing, research | F14: Startups and universities at a subsidised rate
B15: Cost, $B
A16: K9 | B16: Power price ($/kWh) | C16: =Assumptions!$C$69 -> 0.05 | D16: =Assumptions!$C$70 -> 0.13 | E16: =Assumptions!$C$71 -> 0.18 | F16: =Assumptions!$C$72 -> 0.09
A17: K10 | B17: PUE | C17: =Assumptions!$C$74 -> 1.25 | D17: =Assumptions!$C$75 -> 1.2 | E17: =Assumptions!$C$75 -> 1.2 | F17: 1.3
A18: K11 | B18: Up-front capex ($B) | C18: =C7/1000*Assumptions!$C$42 -> 19 | D18: =D7/1000*Assumptions!$C$42 -> 3.8 | E18: =E7/1000*Assumptions!$C$42 -> 7.22 | F18: =F7/1000*Assumptions!$C$42 -> 0.76
A19: K12 | B19: Energy per year ($B) | C19: =C7*1000*C17*Assumptions!$C$53*Assumptions!$C$52*C16/1000000000 -> 0.191625 | D19: =D7*1000*D17*Assumptions!$C$53*Assumptions!$C$52*D16/1000000000 -> 0.0956592 | E19: =E7*1000*E17*Assumptions!$C$53*Assumptions!$C$52*E16/1000000000 -> 0.25165728 | F19: =F7*1000*F17*Assumptions!$C$53*Assumptions!$C$52*F16/1000000000 -> 0.01434888
A20: K13 | B20: Other opex per year ($B) | C20: =C7/1000*(Assumptions!$C$43-Assumptions!$C$45) -> 0.155 | D20: =D7/1000*(Assumptions!$C$43-Assumptions!$C$45) -> 0.031 | E20: =E7/1000*(Assumptions!$C$43-Assumptions!$C$45) -> 0.0589 | F20: =F7/1000*(Assumptions!$C$43-Assumptions!$C$45) -> 0.0062
A21: K14 | B21: Insurance and risk per year ($B) | C21: =C18*Assumptions!$C$77 -> 0.475 | D21: =D18*0.005 -> 0.019 | E21: =E18*0.005 -> 0.0361 | F21: =F18*0.01 -> 0.0076
A22: K15 | B22: Annualised capex ($B) | C22: =C18*Assumptions!$C$9/Assumptions!$C$46+C18*(1-Assumptions!$C$9)/Assumptions!$C$47 -> 3.724 | D22: =D18*Assumptions!$C$9/Assumptions!$C$46+D18*(1-Assumptions!$C$9)/Assumptions!$C$47 -> 0.7448 | E22: =E18*Assumptions!$C$9/Assumptions!$C$46+E18*(1-Assumptions!$C$9)/Assumptions!$C$47 -> 1.41512 | F22: =F18*Assumptions!$C$9/Assumptions!$C$46+F18*(1-Assumptions!$C$9)/Assumptions!$C$47 -> 0.14896
A23: K16 | B23: Annual TCO ($B) | C23: =C22+C19+C20+C21 -> 4.545625 | D23: =D22+D19+D20+D21 -> 0.8904592 | E23: =E22+E19+E20+E21 -> 1.7617773 | F23: =F22+F19+F20+F21 -> 0.17710888
A24: K17 | B24: Years of delay vs US | C24: 0 | D24: 0.5 | E24: =Assumptions!$C$76 -> 1.5 | F24: 1
A25: K18 | B25: Delay cost over life ($B) | C25: =C24*Assumptions!$C$55*10*C23 -> 0 | D25: =D24*Assumptions!$C$55*10*D23 -> 0.24487628 | E25: =E24*Assumptions!$C$55*10*E23 -> 1.4534663 | F25: =F24*Assumptions!$C$55*10*F23 -> 0.097409884
B26: Unit economics
A27: K19 | B27: Utilisation | C27: 0.8 | D27: =Assumptions!$C$52 -> 0.7 | E27: 0.6 | F27: 0.5
A28: K20 | B28: Used GPU-hours per year | C28: =C10*Assumptions!$C$53*C27 -> 1.8348218e+09 | D28: =D10*Assumptions!$C$53*D27 -> 367920000 | E28: =E10*Assumptions!$C$53*E27 -> 599184000 | F28: =F10*Assumptions!$C$53*F27 -> 49006993
A29: K21 | B29: Owner's cost per used GPU-hour ($) | C29: =C23*1000000000/C28 -> 2.4774204 | D29: =D23*1000000000/D28 -> 2.4202522 | E29: =E23*1000000000/E28 -> 2.9402943 | F29: =F23*1000000000/F28 -> 3.6139512
A30: K21b | B30: Break-even price incl. 12% cost of capital ($ per GPU-hour) | C30: =(C23+C18*Assumptions!$C$48)*1000000000/C28 -> 3.7200479 | D30: =(D23+D18*Assumptions!$C$48)*1000000000/D28 -> 3.6596521 | E30: =(E23+E18*Assumptions!$C$48)*1000000000/E28 -> 4.3862608 | F30: =(F23+F18*Assumptions!$C$48)*1000000000/F28 -> 5.4749101
A31: K22 | B31: Price charged per GPU-hour ($) | C31: =Assumptions!$C$57*0.6 -> 6.3 | D31: n/a (internal) | E31: =Assumptions!$C$81 -> 3.1 | F31: =Assumptions!$C$89 -> 1.7
A32: K23 | B32: Gross margin or subsidy per GPU-hour ($) | C32: =C31-C29 -> 3.8225796 | D32: n/a | E32: =E31-E29 -> 0.15970573 | F32: =F31-F29 -> -1.9139512
A33: K24 | B33: Annual subsidy or margin at the hours above ($M) | C33: =C32*C28/1000000 -> 7013.7525 | D33: n/a | E33: =E32*E28/1000000 -> 95.69312 | F33: =F32*F28/1000000 -> -93.796992
A34: K25 | B34: Reading | C34: Sells capacity abroad at a margin while power is cheap and chips are allocated. Exposed to export policy and war risk. | D34: Cost centre for the group. Justified by research velocity and supply-chain sovereignty, not by $/hour. | E34: Priced to European sovereign-cloud rates it cannot reach at 60% utilisation and German power. Needs the 10x leverage and an anchor tenant. | F34: Every subsidised hour costs the state the gap. Cheapest way to give startups compute, most expensive per GPU.
B35: Formulas: GPUs = MW x 1,000 / rack kW x GPUs per rack. Capex = MW / 1,000 x $38B. Energy = MW x 1,000 x PUE x 8,760 x utilisation x $/kWh. TCO = annualised capex + energy + other opex + insurance. $/GPU-hour = TCO / (GPUs x 8,760 x utilisation). Margin or subsidy = price - cost.

Sheet Pricing
A1: Pricing: GPU-hour by route and region, subsidy gaps, and where the margin sits
A2: List prices read Sep-Oct 2026. Owner costs from GigawattTCO.
A4: Line | B4: Item | C4: $ per GPU-hour | D4: Note
B5: Owner's cost (from GigawattTCO, GB200 class, 70% utilisation)
A6: P1 | B6: Own a gigawatt in Saudi Arabia | C6: =GigawattTCO!$D$24 -> 2.4709855
A7: P2 | B7: Own a gigawatt in the United States | C7: =GigawattTCO!$C$24 -> 2.3556522
A8: P3 | B8: Own a gigawatt in South Korea | C8: =GigawattTCO!$E$24 -> 2.4202522
A9: P4 | B9: Own a gigawatt in Germany | C9: =GigawattTCO!$F$24 -> 2.5202522
A10: P5 | B10: Own a gigawatt in Germany incl. 1.5-year delay cost | C10: =GigawattTCO!$F$25 -> 2.728173
A11: P5b | B11: Break-even rental price, US owner incl. 12% cost of capital | C11: =GigawattTCO!$C$27 -> 3.5950521 | D11: From GigawattTCO G18c.
A12: P5c | B12: Break-even rental price, Saudi owner incl. 12% cost of capital | C12: =GigawattTCO!$D$27 -> 3.7103854
A13: P5d | B13: Break-even rental price, German owner incl. 12% cost of capital | C13: =GigawattTCO!$F$27 -> 3.7596521
B14: Rent, Blackwell class
A15: P6 | B15: CoreWeave GB200 on-demand (lowest, May 2026) | C15: =Assumptions!$C$57 -> 10.5 | D15: Carnegie / getdeploying.
A16: P7 | B16: Nebius B200 | C16: =Assumptions!$C$84 -> 8.5 | D16: 14 Oct 2026.
A17: P8 | B17: Verda B200, Finland | C17: =Assumptions!$C$83 -> 6.11 | D17: Sep 2026.
B18: Rent, Hopper class (what most sovereign clouds actually sell)
A19: P9 | B19: Azure H100, West Europe | C19: =Assumptions!$C$80 -> 15.98 | D19: Highest list in Europe.
A20: P10 | B20: AWS Japan H100 | C20: =Assumptions!$C$88 -> 12.3
A21: P11 | B21: AWS H100, Stockholm | C21: =Assumptions!$C$79 -> 7.36
A22: P12 | B22: CoreWeave HGX H100, Europe | C22: =Assumptions!$C$86 -> 6.16
A23: P13 | B23: Sakura Internet H100, Japan (METI-subsidised operator) | C23: =Assumptions!$C$87 -> 6.07 | D23: JPY 990.
A24: P14 | B24: Nebius H100 SXM | C24: =Assumptions!$C$85 -> 4.5
A25: P15 | B25: Scaleway H100 PCIe, Paris | C25: =Assumptions!$C$81 -> 3.1 | D25: EUR 2.87.
A26: P16 | B26: OVHcloud H100, Gravelines | C26: =Assumptions!$C$82 -> 2.99 | D26: Won EUR 180M Commission sovereign-cloud contract.
A27: P17 | B27: Global H100 on-demand median (NVIDIA index, Jun 2026) | C27: =Assumptions!$C$91 -> 2.7
A28: P18 | B28: IndiaAI subsidised rate | C28: =Assumptions!$C$89 -> 1.7 | D28: INR 150.
B29: Spreads
A30: P19 | B30: European sovereign cloud discount to Azure West Europe (P16 / P9) | C30: =C26/C19 -> 0.18710889 | D30: OVHcloud as share of Azure list. European sovereign clouds compete on price, not just jurisdiction.
A31: P20 | B31: Hyperscaler Japan premium over METI-subsidised Sakura (P10 / P13) | C31: =C20/C23 -> 2.0263591
A32: P21 | B32: India subsidy gap per hour vs commercial rate (P18 vs INR 300) | C32: =Assumptions!$C$90-C28 -> 1.7 | D32: Commercial $3.40 less subsidised $1.70.
A33: P22 | B33: India subsidy gap vs owner's cost of a US gigawatt (P2 - P18) | C33: =C7-C28 -> 0.65565223 | D33: What the state eats per hour if the pool costs what a US hyperscaler pays.
A34: P23 | B34: Annual subsidy on 45,000 GPUs at 50% utilisation ($M) | C34: =C33*45000*Assumptions!$C$53*0.5/1000000 -> 129.22905 | D34: P22 x 45,000 x 8,760 x 50% / 1e6. Against IndiaAI's ~$1.2B five-year budget.
A35: P24 | B35: Saudi owner's cost as share of CoreWeave GB200 rental (P1 / P6) | C35: =C6/C15 -> 0.23533196 | D35: The export margin available to a compute exporter before financing cost.
A36: P25 | B36: Germany owner's cost incl. delay as share of Scaleway's price (P5 / P15) | C36: =C10/C25 -> 0.88005582 | D36: Below 100% means a German gigafactory can undercut existing European sovereign clouds on cash cost. Add the 12% cost of capital (P5d) and the comparison flips.
A37: P25b | B37: German break-even incl. cost of capital as share of Scaleway's price (P5d / P15) | C37: =C13/C25 -> 1.212791 | D37: Above 100% means the gigafactory cannot earn its cost of capital selling at today's European sovereign-cloud prices.
A38: P25c | B38: Saudi break-even incl. cost of capital as share of CoreWeave GB200 (P5c / P6) | C38: =C12/C15 -> 0.35337004 | D38: The exporter still clears its capital charge with room to spare.
B39: Where the margin sits
A40: P26 | B40: GB300 chip value in US export approvals ($ per chip) | C40: =Assumptions!$C$93 -> 28571 | D40: 35,000 chips ~ $1B.
A41: P27 | B41: NVIDIA cost of goods per chip at 75% gross margin ($) | C41: =C40*(1-Assumptions!$C$92) -> 7142.75 | D41: P26 x 25%.
A42: P28 | B42: All-in capex per GPU in a gigawatt ($) | C42: =GigawattTCO!$C$30 -> 63333.333 | D42: From GigawattTCO: $38B / GPUs in 1 GW.
A43: P29 | B43: Chip as share of all-in capex per GPU (P26 / P28) | C43: =C40/C42 -> 0.45112105 | D43: The rest is the server, rack, network, storage, building and power plant.
A44: P30 | B44: Reading | D44: In a sovereign deal the chip is under half the money. The state controls the land, power and permits, which is why the Gulf can clear a gigawatt in 2.5 years and Northumberland takes nine. Pricing power in this market belongs to whoever controls time to power, and today that is the Gulf and NVIDIA's allocation desk, not the cloud.

Sheet Value
A1: Value: what sovereign compute is worth
A2: Macro claims are large and soft. The usable tests are ratios: value per dollar invested, revenue per compute dollar, and whether the owner can cover cost of capital.
A4: Line | B4: Item | C4: Value | D4: Formula (in words)
B5: A. Macro: GDP uplift that depends on in-country compute
A6: VA1 | B6: PwC: AI uplift to global GDP by 2030 (share) | C6: =Assumptions!$C$96 -> 0.14 | D6: 14%.
A7: VA2 | B7: Share of that uplift requiring in-country compute | C7: =Assumptions!$C$109 -> 0.25 | D7: Assumption 25%.
A8: VA3 | B8: Saudi Arabia: annual GDP uplift at stake ($B) | C8: =Assumptions!$C$104*1000*C6*C7 -> 38.5 | D8: GDP x 14% x 25%.
A9: VA4 | B9: Saudi Arabia: HUMAIN announced capex to 2030 ($B) | C9: =1.9*Assumptions!$C$42 -> 72.2 | D9: 1.9 GW x $38B.
A10: VA5 | B10: Years of uplift to pay back the capex | C10: =C9/C8 -> 1.8753247 | D10: VA4 / VA3.
A11: VA6 | B11: EU: annual GDP uplift at stake ($B) | C11: =Assumptions!$C$106*1000*C6*C7 -> 665
A12: VA7 | B12: EU: gigafactories plus AI factories capex ($B) | C12: =1.7*Assumptions!$C$42 -> 64.6 | D12: 1.7 GW announced x $38B.
A13: VA8 | B13: Years of uplift to pay back | C13: =C12/C11 -> 0.097142857
A14: VA9 | B14: India: annual GDP uplift at stake ($B) | C14: =Assumptions!$C$107*1000*C6*C7 -> 140
A15: VA10 | B15: India: IndiaAI capex equivalent ($B) | C15: =0.09*Assumptions!$C$42 -> 3.42 | D15: 90 MW x $38B.
A16: VA11 | B16: Years of uplift to pay back | C16: =C15/C14 -> 0.024428571 | D16: A rounding error. India's constraint is not capital but power, chips and talent.
A17: VA12 | B17: Thailand: annual GDP uplift at stake ($B) | C17: =Assumptions!$C$108*1000*C6*C7 -> 18.55
A18: VA13 | B18: Thailand: Gulf Development 2 GW plan capex ($B) | C18: =2*Assumptions!$C$42 -> 76 | D18: 2 GW x $38B. Far beyond domestic need, so it only works as an export or hyperscaler-tenant play.
A19: VA14 | B19: Years of uplift to pay back | C19: =C18/C17 -> 4.097035
B20: B. Micro: value per dollar of infrastructure
A21: VB1 | B21: Google Bangkok region: economic value claimed per dollar invested | C21: =Assumptions!$C$98/Assumptions!$C$99 -> 41 | D21: $41B / $1B (Public First for Google). A vendor-commissioned multiplier.
A22: VB2 | B22: Frontier lab revenue per dollar of compute (Anthropic) | C22: =Assumptions!$C$100 -> 1.7 | D22: $1.70. The best disclosed return on compute in the industry.
A23: VB3 | B23: Gartner: revenue needed vs revenue available to AI data center owners through 2030 | C23: =Assumptions!$C$102/Assumptions!$C$101 -> 0.42352941 | D23: $3.6T / $8.5T. Owners as a class cover 42% of what a 12% return requires.
A24: VB4 | B24: Infrastructure exposed to impairment by 2030 ($T) | C24: =Assumptions!$C$103 -> 3.5 | D24: >$3.5T.
B25: C. Owner's economics for a sovereign gigawatt
A26: VC1 | B26: Saudi gigawatt annual TCO ($B) | C26: =GigawattTCO!$D$17 -> 9.09125
A27: VC2 | B27: Revenue if sold at 60% of CoreWeave GB200 rate, 80% utilisation ($B) | C27: =Assumptions!$C$57*0.6*GigawattTCO!$C$22*Assumptions!$C$53*0.8/1000000000 -> 26.49024 | D27: $10.50 x 60% x GPUs in 1 GW x 8,760 x 80% / 1e9.
A28: VC3 | B28: Operating margin before financing | C28: =(C27-C26)/C27 -> 0.65680756 | D28: (VC2 - VC1) / VC2.
A29: VC3b | B29: Operating margin after 12% cost of capital on $38B | C29: =(C27-C26-Assumptions!$C$42*Assumptions!$C$48)/C27 -> 0.48466869 | D29: (VC2 - VC1 - $38B x 12%) / VC2.
A30: VC4 | B30: German gigawatt annual TCO ($B) | C30: =GigawattTCO!$F$17 -> 9.272512
A31: VC5 | B31: Revenue at Scaleway's Hopper-class price, 60% utilisation ($B) | C31: =Assumptions!$C$81*GigawattTCO!$C$22*Assumptions!$C$53*0.6/1000000000 -> 9.77616 | D31: EUR 2.87 x GPUs x 8,760 x 60% / 1e9. If the gigafactory has to compete with existing European clouds on price.
A32: VC6 | B32: Operating margin before financing | C32: =(C31-C30)/C31 -> 0.051517978 | D32: Negative means the gigafactory cannot be run as a cloud business at today's European prices. It is a research instrument and must be valued as one.
A33: VC6b | B33: Operating margin after 12% cost of capital | C33: =(C31-C30-Assumptions!$C$42*Assumptions!$C$48)/C31 -> -0.41492283 | D33: (VC5 - VC4 - $38B x 12%) / VC5. Negative means a European gigafactory cannot be run as a cloud business at today's European prices. It is a research instrument and must be valued as one.
A34: VC7 | B34: Revenue needed to cover German TCO plus 12% cost of capital at 60% utilisation, $ per GPU-hour | C34: =(C30+Assumptions!$C$42*Assumptions!$C$48)*1000000000/(GigawattTCO!$C$22*Assumptions!$C$53*0.6) -> 4.3862608 | D34: (VC4 + $38B x 12%) x 1e9 / used hours. The Blackwell-class price a gigafactory would have to charge.
B35: D. The strategic value nobody prices
A36: VD1 | B36: Reading | D36: Three things do not appear in the ratios above. Optionality: a state with its own gigawatt can run a national model when a foreign API is cut off. Industrial pull-through: Korea's 260,000 GPUs are for Hyundai and SK's products, not for selling compute. Bargaining power: HUMAIN's 35,000-chip export approval and $23B of agreements were negotiated at head-of-state level. These are real and they explain why the capital keeps coming after the spreadsheet says stop.

Sheet Sources
A1: Sources
A2: Numbering matches the article at esthercs.dev/research/sovereign-ai.
A4: No. | B4: Source | C4: Date | D4: URL
A5: 1 | B5: Fortune, Nvidia's European spending spree is about much more than Europe (sovereign revenue >$30B FY26, $8B into Europe, Nscale) | C5: 15 Oct 2026 | D5: https://fortune.com/2026/10/15/nvidias-european-spending-spree-is-about-much-more-than-europe/
A6: 2 | B6: Air Street Capital, State of AI Report 2026 (NVIDIA >$30B sovereign AI revenue FY2026; hyperscaler capex ~$733B) | C6: Oct 2026 | D6: https://www.stateof.ai/
A7: 3 | B7: vision2030.ai, HUMAIN's AI Infrastructure Machine: 600,000 GPUs, $77 Billion, 6.6 GW | C7: 2026 | D7: https://vision2030.ai/analysis/humain-ai-infrastructure/
A8: 4 | B8: Saudi Market Research Consulting, HUMAIN Saudi Arabia: A Bold Sovereign AI Push | C8: 2025-2026 | D8: https://saudimarketresearchconsulting.com/insights/articles/humain-saudi-arabia-a-bold-sovereign-ai-push-reshaping-infrastructure-and-markets
A9: 5 | B9: Qualcomm, HUMAIN and Qualcomm to deploy AI infrastructure in Saudi Arabia (200 MW) | C9: Oct 2025 | D9: https://www.qualcomm.com/news/releases/2025/10/humain-and-qualcomm-to-deploy-ai-infrastructure-in-saudi-arabia-
A10: 6 | B10: US Department of Commerce, Statement on UAE and Saudi Chip Exports (35,000 GB300-equivalent each) | C10: 19 Nov 2025 | D10: https://www.commerce.gov/news/press-releases/2025/11/statement-uae-and-saudi-chip-exports
A11: 7 | B11: Reuters, US authorizes export of advanced American semiconductors to companies in Saudi, UAE | C11: 19 Nov 2025 | D11: https://www.reuters.com/business/us-authorizes-export-advanced-american-semiconductors-companies-saudi-uae-2025-11-19/
A12: 8 | B12: OpenAI, Introducing Stargate UAE (1 GW, 200 MW in 2026) | C12: May 2025 | D12: https://openai.com/index/introducing-stargate-uae/
A13: 9 | B13: G42, Global Tech Alliance Launches Stargate UAE | C13: May 2025 | D13: https://www.g42.ai/resources/news/global-tech-alliance-launches-stargate-uae
A14: 10 | B14: The Tech Capital, First 200 MW of Stargate UAE will come online in 2026 says G42 chief (5 GW campus) | C14: 15 Oct 2025 | D14: https://thetechcapital.com/first-200mw-of-stargate-uae-will-come-online-in-2026-says-g42-chief
A15: 11 | B15: European Commission, AI Factories policy page (19 AI Factories, up to seven gigafactories, EUR 10B) | C15: 12 Aug 2026 | D15: https://digital-strategy.ec.europa.eu/en/policies/ai-factories
A16: 12 | B16: EIB Group and European Commission join forces to finance AI gigafactories (~100,000 chips each) | C16: 2025 | D16: https://www.eib.org/en/press/all/2025-491-eib-group-and-european-commission-join-forces-to-finance-ai-gigafactories
... A48: 44 | B48: Avid Solutions summarising McKinsey ($5.2T for 156 GW by 2030) and JLL ($11.3M/MW construction 2026) | C48: Jan 2026 | D48: https://avidsolutionsinc.com/13-data-center-growth-projections-that-will-shape-2026-2030/
